{"GameMode":"FA+","MachineGuid":"2795733f34c89ebd","ProductID":"ITGmania","ProductVersion":"0.7.0","Score":{"DateTime":"2024-02-04 15:31:30","Disqualified":false,"Grade":"Tier13","Guid":"9f668809-0596-49c7-aa72-92505a01c591","HoldNoteScores":{"Held":0,"LetGo":0,"MissedHold":0},"MaxCombo":50,"Modifiers":"C570, 10% Mini, NoMines, FailImmediateContinue, Overhead, Default","PercentDP":0.69840002059936523,"PlayerGuid":"df4984970b65a1fc","Radar":{"Hands":0,"Holds":0,"Jumps":7,"Mines":0,"Notes":298,"Rolls":0,"TapsAndHolds":292},"Score":66638725,"SurviveSeconds":95.835670471191406,"TapNoteScores":{"AvoidMine":0,"CheckpointHit":0,"CheckpointMiss":0,"HitMine":0,"Miss":17,"W1":138,"W2":55,"W3":68,"W4":30,"W5":5}},"Song":{"Artist":"BUS\u2605STOP","BPM":[144,144],"Dir":"/Songs/DDR 1stMix-5thMix/KICK THE CAN/","Group":"DDR 1stMix-5thMix","MusicLengthSeconds":94.971000671386719,"RandomBPM":false,"Title":"KICK THE CAN","TranslitArtist":"BUS\u2605STOP","TranslitTitle":"KICK THE CAN"},"Steps":{"AuthorCredit":"","Description":"","Difficulty":"Hard","Meter":7,"Radar":{"Hands":0,"Holds":0,"Jumps":7,"Mines":0,"Notes":320,"Rolls":0,"TapsAndHolds":313},"StepsType":"dance-single"},"Theme":"Simply Love","ThemeVersion":"5.3.0 for ITGmania","Version":1}
