<?xml version="1.0" encoding="UTF-8" ?>

<Stats>
<MachineGuid>403d15c592378cca</MachineGuid>
<RecentSongScores>
<HighScoreForASongAndSteps>
<Song Dir='Songs/Floor Filler/WORMHOLE/'/>
<Steps Difficulty='Easy' StepsType='dance-single'/>
<HighScore>
<Name></Name>
<Grade>Tier10</Grade>
<Score>39</Score>
<PercentDP>0.803600</PercentDP>
<SurviveSeconds>112.577309</SurviveSeconds>
<MaxCombo>79</MaxCombo>
<StageAward></StageAward>
<PeakComboAward></PeakComboAward>
<Modifiers>NoHideLights, C380, FailImmediateContinue, Overhead, Default</Modifiers>
<DateTime>2025-06-19 14:59:44</DateTime>
<PlayerGuid>d876307e83faa0ea</PlayerGuid>
<MachineGuid>403d15c592378cca</MachineGuid>
<ProductID>1</ProductID>
<TapNoteScores>
<HitMine>0</HitMine>
<AvoidMine>0</AvoidMine>
<CheckpointMiss>0</CheckpointMiss>
<Miss>3</Miss>
<W5>4</W5>
<W4>4</W4>
<W3>31</W3>
<W2>57</W2>
<W1>143</W1>
<CheckpointHit>0</CheckpointHit>
</TapNoteScores>
<HoldNoteScores>
<LetGo>1</LetGo>
<Held>32</Held>
<MissedHold>0</MissedHold>
</HoldNoteScores>
<RadarValues>
<Stream>0.835878</Stream>
<Voltage>0.350659</Voltage>
<Air>0.900000</Air>
<Freeze>0.969697</Freeze>
<Chaos>0.803636</Chaos>
<Notes>255.000000</Notes>
<TapsAndHolds>235</TapsAndHolds>
<Jumps>20</Jumps>
<Holds>32</Holds>
<Mines>0</Mines>
<Hands>0</Hands>
<Rolls>0</Rolls>
<Lifts>0</Lifts>
<Fakes>0</Fakes>
</RadarValues>
<LifeRemainingSeconds>0.000000</LifeRemainingSeconds>
<Disqualified>0</Disqualified>
<Pad>33</Pad>
<StageGuid>53c59215-c5e4-4754-aa35-9f166f519a49</StageGuid>
<Guid>d42e5ca0-f3a6-4321-a062-34a0444ed972</Guid>
</HighScore>
</HighScoreForASongAndSteps>
</RecentSongScores>
</Stats>
