<?xml version="1.0" encoding="UTF-8" ?>

<Stats>
<MachineGuid>403d15c592378cca</MachineGuid>
<RecentSongScores>
<HighScoreForASongAndSteps>
<Song Dir='Songs/Misc. Collected/Lovers (Pure Mix)/'/>
<Steps Difficulty='Hard' StepsType='dance-single'/>
<HighScore>
<Name></Name>
<Grade>Tier10</Grade>
<Score>55</Score>
<PercentDP>0.814900</PercentDP>
<SurviveSeconds>126.860725</SurviveSeconds>
<MaxCombo>81</MaxCombo>
<StageAward></StageAward>
<PeakComboAward></PeakComboAward>
<Modifiers>NoHideLights, C580, 10% Mini, FailImmediateContinue, Overhead, Default</Modifiers>
<DateTime>2025-04-24 18:06:40</DateTime>
<PlayerGuid>4ad3a19834ee56bd</PlayerGuid>
<MachineGuid>403d15c592378cca</MachineGuid>
<ProductID>1</ProductID>
<TapNoteScores>
<HitMine>0</HitMine>
<AvoidMine>0</AvoidMine>
<CheckpointMiss>0</CheckpointMiss>
<Miss>5</Miss>
<W5>1</W5>
<W4>1</W4>
<W3>41</W3>
<W2>86</W2>
<W1>184</W1>
<CheckpointHit>0</CheckpointHit>
</TapNoteScores>
<HoldNoteScores>
<LetGo>0</LetGo>
<Held>17</Held>
<MissedHold>0</MissedHold>
</HoldNoteScores>
<RadarValues>
<Stream>0.849275</Stream>
<Voltage>0.325976</Voltage>
<Air>0.814815</Air>
<Freeze>1.000000</Freeze>
<Chaos>0.814925</Chaos>
<Notes>339.000000</Notes>
<TapsAndHolds>312</TapsAndHolds>
<Jumps>27</Jumps>
<Holds>17</Holds>
<Mines>0</Mines>
<Hands>0</Hands>
<Rolls>0</Rolls>
<Lifts>0</Lifts>
<Fakes>0</Fakes>
</RadarValues>
<LifeRemainingSeconds>0.000000</LifeRemainingSeconds>
<Disqualified>0</Disqualified>
<Pad>33</Pad>
<StageGuid>a0ddb9b8-f0f5-46d0-a521-d2415b278d00</StageGuid>
<Guid>f4701ff4-9ba0-4490-a39a-0bf56eafcab2</Guid>
</HighScore>
</HighScoreForASongAndSteps>
</RecentSongScores>
</Stats>
