<?xml version="1.0" encoding="UTF-8" ?>

<Stats>
<MachineGuid>403d15c592378cca</MachineGuid>
<RecentSongScores>
<HighScoreForASongAndSteps>
<Song Dir='Songs/Cosmic Reincarnate/Ramp! (The Logical Song)/'/>
<Steps Difficulty='Hard' StepsType='dance-single'/>
<HighScore>
<Name></Name>
<Grade>Tier07</Grade>
<Score>82</Score>
<PercentDP>0.904000</PercentDP>
<SurviveSeconds>109.496475</SurviveSeconds>
<MaxCombo>206</MaxCombo>
<StageAward></StageAward>
<PeakComboAward></PeakComboAward>
<Modifiers>NoHideLights, C565, 10% Mini, FailImmediateContinue, Overhead, Default</Modifiers>
<DateTime>2025-06-09 17:44:01</DateTime>
<PlayerGuid>4ad3a19834ee56bd</PlayerGuid>
<MachineGuid>403d15c592378cca</MachineGuid>
<ProductID>1</ProductID>
<TapNoteScores>
<HitMine>0</HitMine>
<AvoidMine>0</AvoidMine>
<CheckpointMiss>0</CheckpointMiss>
<Miss>2</Miss>
<W5>0</W5>
<W4>0</W4>
<W3>13</W3>
<W2>83</W2>
<W1>225</W1>
<CheckpointHit>0</CheckpointHit>
</TapNoteScores>
<HoldNoteScores>
<LetGo>0</LetGo>
<Held>2</Held>
<MissedHold>0</MissedHold>
</HoldNoteScores>
<RadarValues>
<Stream>0.950867</Stream>
<Voltage>0.622314</Voltage>
<Air>0.782609</Air>
<Freeze>1.000000</Freeze>
<Chaos>0.904000</Chaos>
<Notes>343.000000</Notes>
<TapsAndHolds>322</TapsAndHolds>
<Jumps>23</Jumps>
<Holds>2</Holds>
<Mines>0</Mines>
<Hands>0</Hands>
<Rolls>0</Rolls>
<Lifts>0</Lifts>
<Fakes>0</Fakes>
</RadarValues>
<LifeRemainingSeconds>0.000000</LifeRemainingSeconds>
<Disqualified>0</Disqualified>
<Pad>33</Pad>
<StageGuid>34234547-ddf3-405e-a93d-032f8500e372</StageGuid>
<Guid>f986f430-dbac-4e0f-a92d-c520071badf9</Guid>
</HighScore>
</HighScoreForASongAndSteps>
</RecentSongScores>
</Stats>
