<?xml version="1.0" encoding="UTF-8" ?>

<Stats>
<MachineGuid>403d15c592378cca</MachineGuid>
<RecentSongScores>
<HighScoreForASongAndSteps>
<Song Dir='Songs/Misc. Collected/Flash Man/'/>
<Steps Difficulty='Hard' StepsType='dance-single'/>
<HighScore>
<Name></Name>
<Grade>Tier11</Grade>
<Score>56</Score>
<PercentDP>0.765800</PercentDP>
<SurviveSeconds>91.141052</SurviveSeconds>
<MaxCombo>150</MaxCombo>
<StageAward></StageAward>
<PeakComboAward></PeakComboAward>
<Modifiers>NoHideLights, C580, 10% Mini, FailImmediateContinue, Overhead, Default</Modifiers>
<DateTime>2025-08-15 16:42:23</DateTime>
<PlayerGuid>4ad3a19834ee56bd</PlayerGuid>
<MachineGuid>403d15c592378cca</MachineGuid>
<ProductID>1</ProductID>
<TapNoteScores>
<HitMine>0</HitMine>
<AvoidMine>0</AvoidMine>
<CheckpointMiss>0</CheckpointMiss>
<Miss>9</Miss>
<W5>3</W5>
<W4>1</W4>
<W3>52</W3>
<W2>102</W2>
<W1>168</W1>
<CheckpointHit>0</CheckpointHit>
</TapNoteScores>
<HoldNoteScores>
<LetGo>1</LetGo>
<Held>55</Held>
<MissedHold>1</MissedHold>
</HoldNoteScores>
<RadarValues>
<Stream>0.805970</Stream>
<Voltage>0.480017</Voltage>
<Air>0.000000</Air>
<Freeze>0.964912</Freeze>
<Chaos>0.765816</Chaos>
<Notes>323.000000</Notes>
<TapsAndHolds>323</TapsAndHolds>
<Jumps>0</Jumps>
<Holds>55</Holds>
<Mines>0</Mines>
<Hands>0</Hands>
<Rolls>0</Rolls>
<Lifts>0</Lifts>
<Fakes>0</Fakes>
</RadarValues>
<LifeRemainingSeconds>0.000000</LifeRemainingSeconds>
<Disqualified>0</Disqualified>
<Pad>33</Pad>
<StageGuid>7450883f-5424-4e2d-ae99-031cd72ce087</StageGuid>
<Guid>d147d0e2-c977-4289-a033-53106d68816a</Guid>
</HighScore>
</HighScoreForASongAndSteps>
</RecentSongScores>
</Stats>
