<?xml version="1.0" encoding="UTF-8" ?>

<Stats>
<MachineGuid>403d15c592378cca</MachineGuid>
<RecentSongScores>
<HighScoreForASongAndSteps>
<Song Dir='Songs/JBEAN Originals - 2023/Do Si Do/'/>
<Steps Difficulty='Challenge' StepsType='dance-single'/>
<HighScore>
<Name></Name>
<Grade>Tier11</Grade>
<Score>64</Score>
<PercentDP>0.767700</PercentDP>
<SurviveSeconds>99.145340</SurviveSeconds>
<MaxCombo>134</MaxCombo>
<StageAward></StageAward>
<PeakComboAward></PeakComboAward>
<Modifiers>NoHideLights, C565, 10% Mini, FailImmediateContinue, Overhead, Default</Modifiers>
<DateTime>2025-06-09 18:09:29</DateTime>
<PlayerGuid>4ad3a19834ee56bd</PlayerGuid>
<MachineGuid>403d15c592378cca</MachineGuid>
<ProductID>1</ProductID>
<TapNoteScores>
<HitMine>0</HitMine>
<AvoidMine>0</AvoidMine>
<CheckpointMiss>0</CheckpointMiss>
<Miss>7</Miss>
<W5>5</W5>
<W4>5</W4>
<W3>67</W3>
<W2>125</W2>
<W1>235</W1>
<CheckpointHit>0</CheckpointHit>
</TapNoteScores>
<HoldNoteScores>
<LetGo>0</LetGo>
<Held>8</Held>
<MissedHold>0</MissedHold>
</HoldNoteScores>
<RadarValues>
<Stream>0.811688</Stream>
<Voltage>0.306793</Voltage>
<Air>0.722222</Air>
<Freeze>1.000000</Freeze>
<Chaos>0.767699</Chaos>
<Notes>450.000000</Notes>
<TapsAndHolds>432</TapsAndHolds>
<Jumps>17</Jumps>
<Holds>8</Holds>
<Mines>0</Mines>
<Hands>0</Hands>
<Rolls>0</Rolls>
<Lifts>0</Lifts>
<Fakes>0</Fakes>
</RadarValues>
<LifeRemainingSeconds>0.000000</LifeRemainingSeconds>
<Disqualified>0</Disqualified>
<Pad>33</Pad>
<StageGuid>6c684e3b-0a44-41b9-a0b1-d4a4f78268ea</StageGuid>
<Guid>f244f87b-5797-4676-ac42-f8ec3c4ca435</Guid>
</HighScore>
</HighScoreForASongAndSteps>
</RecentSongScores>
</Stats>
