<?xml version="1.0" encoding="UTF-8" ?>

<Stats>
<MachineGuid>403d15c592378cca</MachineGuid>
<RecentSongScores>
<HighScoreForASongAndSteps>
<Song Dir='Songs/Misc. Collected/Driver/'/>
<Steps Difficulty='Medium' StepsType='dance-single'/>
<HighScore>
<Name></Name>
<Grade>Failed</Grade>
<Score>40</Score>
<PercentDP>0.522000</PercentDP>
<SurviveSeconds>88.959663</SurviveSeconds>
<MaxCombo>74</MaxCombo>
<StageAward></StageAward>
<PeakComboAward></PeakComboAward>
<Modifiers>NoHideLights, C380, FailImmediateContinue, Overhead, Default</Modifiers>
<DateTime>2025-06-09 19:13:03</DateTime>
<PlayerGuid>d876307e83faa0ea</PlayerGuid>
<MachineGuid>403d15c592378cca</MachineGuid>
<ProductID>1</ProductID>
<TapNoteScores>
<HitMine>0</HitMine>
<AvoidMine>0</AvoidMine>
<CheckpointMiss>0</CheckpointMiss>
<Miss>16</Miss>
<W5>8</W5>
<W4>8</W4>
<W3>58</W3>
<W2>75</W2>
<W1>117</W1>
<CheckpointHit>0</CheckpointHit>
</TapNoteScores>
<HoldNoteScores>
<LetGo>0</LetGo>
<Held>18</Held>
<MissedHold>0</MissedHold>
</HoldNoteScores>
<RadarValues>
<Stream>0.687075</Stream>
<Voltage>0.253575</Voltage>
<Air>0.750000</Air>
<Freeze>1.000000</Freeze>
<Chaos>0.522000</Chaos>
<Notes>270.000000</Notes>
<TapsAndHolds>258</TapsAndHolds>
<Jumps>12</Jumps>
<Holds>18</Holds>
<Mines>0</Mines>
<Hands>0</Hands>
<Rolls>0</Rolls>
<Lifts>0</Lifts>
<Fakes>0</Fakes>
</RadarValues>
<LifeRemainingSeconds>0.000000</LifeRemainingSeconds>
<Disqualified>0</Disqualified>
<Pad>33</Pad>
<StageGuid>1159d77d-771d-4f47-a54e-2157e9088a4a</StageGuid>
<Guid>c0ac5474-686f-4e48-a0ad-b119b1f66ace</Guid>
</HighScore>
</HighScoreForASongAndSteps>
</RecentSongScores>
</Stats>
