<?xml version="1.0" encoding="UTF-8" ?>

<Stats>
<MachineGuid>403d15c592378cca</MachineGuid>
<RecentSongScores>
<HighScoreForASongAndSteps>
<Song Dir='Songs/Misc. Collected/Swag/'/>
<Steps Difficulty='Hard' StepsType='dance-single'/>
<HighScore>
<Name></Name>
<Grade>Tier12</Grade>
<Score>75</Score>
<PercentDP>0.752400</PercentDP>
<SurviveSeconds>141.960114</SurviveSeconds>
<MaxCombo>201</MaxCombo>
<StageAward></StageAward>
<PeakComboAward></PeakComboAward>
<Modifiers>NoHideLights, C560, 10% Mini, FailImmediateContinue, Overhead, Default</Modifiers>
<DateTime>2025-04-26 15:51:20</DateTime>
<PlayerGuid>4ad3a19834ee56bd</PlayerGuid>
<MachineGuid>403d15c592378cca</MachineGuid>
<ProductID>1</ProductID>
<TapNoteScores>
<HitMine>0</HitMine>
<AvoidMine>0</AvoidMine>
<CheckpointMiss>0</CheckpointMiss>
<Miss>4</Miss>
<W5>4</W5>
<W4>3</W4>
<W3>133</W3>
<W2>166</W2>
<W1>220</W1>
<CheckpointHit>0</CheckpointHit>
</TapNoteScores>
<HoldNoteScores>
<LetGo>0</LetGo>
<Held>29</Held>
<MissedHold>0</MissedHold>
</HoldNoteScores>
<RadarValues>
<Stream>0.729242</Stream>
<Voltage>0.387001</Voltage>
<Air>0.541667</Air>
<Freeze>1.000000</Freeze>
<Chaos>0.752415</Chaos>
<Notes>546.000000</Notes>
<TapsAndHolds>523</TapsAndHolds>
<Jumps>22</Jumps>
<Holds>29</Holds>
<Mines>0</Mines>
<Hands>0</Hands>
<Rolls>0</Rolls>
<Lifts>0</Lifts>
<Fakes>0</Fakes>
</RadarValues>
<LifeRemainingSeconds>0.000000</LifeRemainingSeconds>
<Disqualified>0</Disqualified>
<Pad>33</Pad>
<StageGuid>c96a6b5c-7e58-4e7e-aba4-6457d0ecc7fe</StageGuid>
<Guid>8218e25b-1594-432b-a6e1-3f5f00fd1236</Guid>
</HighScore>
</HighScoreForASongAndSteps>
</RecentSongScores>
</Stats>
