<?xml version="1.0" encoding="UTF-8" ?>

<Stats>
<MachineGuid>403d15c592378cca</MachineGuid>
<RecentSongScores>
<HighScoreForASongAndSteps>
<Song Dir='Songs/Misc. Collected/New Rules/'/>
<Steps Difficulty='Beginner' StepsType='dance-single'/>
<HighScore>
<Name></Name>
<Grade>Tier17</Grade>
<Score>6</Score>
<PercentDP>0.381800</PercentDP>
<SurviveSeconds>96.568085</SurviveSeconds>
<MaxCombo>21</MaxCombo>
<StageAward></StageAward>
<PeakComboAward></PeakComboAward>
<Modifiers>NoHideLights, C300, FailImmediateContinue, Overhead</Modifiers>
<DateTime>2025-04-14 16:30:14</DateTime>
<PlayerGuid>2dde4d6e8737681e</PlayerGuid>
<MachineGuid>403d15c592378cca</MachineGuid>
<ProductID>1</ProductID>
<TapNoteScores>
<HitMine>0</HitMine>
<AvoidMine>0</AvoidMine>
<CheckpointMiss>0</CheckpointMiss>
<Miss>3</Miss>
<W5>0</W5>
<W4>3</W4>
<W3>29</W3>
<W2>7</W2>
<W1>9</W1>
<CheckpointHit>0</CheckpointHit>
</TapNoteScores>
<HoldNoteScores>
<LetGo>2</LetGo>
<Held>2</Held>
<MissedHold>0</MissedHold>
</HoldNoteScores>
<RadarValues>
<Stream>0.315789</Stream>
<Voltage>0.309454</Voltage>
<Air>0.500000</Air>
<Freeze>0.500000</Freeze>
<Chaos>0.381818</Chaos>
<Notes>54.000000</Notes>
<TapsAndHolds>48</TapsAndHolds>
<Jumps>6</Jumps>
<Holds>2</Holds>
<Mines>0</Mines>
<Hands>0</Hands>
<Rolls>0</Rolls>
<Lifts>0</Lifts>
<Fakes>0</Fakes>
</RadarValues>
<LifeRemainingSeconds>0.000000</LifeRemainingSeconds>
<Disqualified>0</Disqualified>
<Pad>33</Pad>
<StageGuid>69402db5-26cd-4326-ae77-7553c35514ab</StageGuid>
<Guid>11e1afa5-1b76-4451-adf7-51f767e4133b</Guid>
</HighScore>
</HighScoreForASongAndSteps>
</RecentSongScores>
</Stats>
