<?xml version="1.0" encoding="UTF-8" ?>

<Stats>
<MachineGuid>403d15c592378cca</MachineGuid>
<RecentSongScores>
<HighScoreForASongAndSteps>
<Song Dir='Songs/Anthem Series - Garage Rewind/Lets get it Started/'/>
<Steps Difficulty='Challenge' StepsType='dance-single'/>
<HighScore>
<Name></Name>
<Grade>Tier07</Grade>
<Score>110</Score>
<PercentDP>0.893800</PercentDP>
<SurviveSeconds>153.150162</SurviveSeconds>
<MaxCombo>190</MaxCombo>
<StageAward></StageAward>
<PeakComboAward></PeakComboAward>
<Modifiers>NoHideLights, C585, 10% Mini, FailImmediateContinue, Overhead, Default</Modifiers>
<DateTime>2025-12-20 14:21:35</DateTime>
<PlayerGuid>4ad3a19834ee56bd</PlayerGuid>
<MachineGuid>403d15c592378cca</MachineGuid>
<ProductID>1</ProductID>
<TapNoteScores>
<HitMine>0</HitMine>
<AvoidMine>0</AvoidMine>
<CheckpointMiss>0</CheckpointMiss>
<Miss>5</Miss>
<W5>0</W5>
<W4>3</W4>
<W3>43</W3>
<W2>150</W2>
<W1>391</W1>
<CheckpointHit>0</CheckpointHit>
</TapNoteScores>
<HoldNoteScores>
<LetGo>0</LetGo>
<Held>139</Held>
<MissedHold>2</MissedHold>
</HoldNoteScores>
<RadarValues>
<Stream>0.915309</Stream>
<Voltage>0.319228</Voltage>
<Air>0.954545</Air>
<Freeze>0.985714</Freeze>
<Chaos>0.893861</Chaos>
<Notes>609.000000</Notes>
<TapsAndHolds>588</TapsAndHolds>
<Jumps>22</Jumps>
<Holds>138</Holds>
<Mines>0</Mines>
<Hands>1</Hands>
<Rolls>1</Rolls>
<Lifts>0</Lifts>
<Fakes>0</Fakes>
</RadarValues>
<LifeRemainingSeconds>0.000000</LifeRemainingSeconds>
<Disqualified>0</Disqualified>
<Pad>33</Pad>
<StageGuid>7de5cf75-09f7-4e35-a3a7-caa560a1678d</StageGuid>
<Guid>0eb5da5b-354a-404d-a926-14daa21f19db</Guid>
</HighScore>
</HighScoreForASongAndSteps>
</RecentSongScores>
</Stats>
