<?xml version="1.0" encoding="UTF-8" ?>

<Stats>
<MachineGuid>403d15c592378cca</MachineGuid>
<RecentSongScores>
<HighScoreForASongAndSteps>
<Song Dir='Songs/80s Greatest Hits Volume 1/Don&apos;t Stop Me Now/'/>
<Steps Difficulty='Medium' StepsType='dance-single'/>
<HighScore>
<Name></Name>
<Grade>Tier10</Grade>
<Score>44</Score>
<PercentDP>0.801000</PercentDP>
<SurviveSeconds>166.852356</SurviveSeconds>
<MaxCombo>87</MaxCombo>
<StageAward></StageAward>
<PeakComboAward></PeakComboAward>
<Modifiers>NoHideLights, C380, FailImmediateContinue, Overhead, Default</Modifiers>
<DateTime>2025-05-07 22:14:00</DateTime>
<PlayerGuid>d876307e83faa0ea</PlayerGuid>
<MachineGuid>403d15c592378cca</MachineGuid>
<ProductID>1</ProductID>
<TapNoteScores>
<HitMine>0</HitMine>
<AvoidMine>0</AvoidMine>
<CheckpointMiss>0</CheckpointMiss>
<Miss>1</Miss>
<W5>2</W5>
<W4>8</W4>
<W3>67</W3>
<W2>82</W2>
<W1>177</W1>
<CheckpointHit>0</CheckpointHit>
</TapNoteScores>
<HoldNoteScores>
<LetGo>2</LetGo>
<Held>35</Held>
<MissedHold>0</MissedHold>
</HoldNoteScores>
<RadarValues>
<Stream>0.761236</Stream>
<Voltage>0.246140</Voltage>
<Air>0.736842</Air>
<Freeze>0.945946</Freeze>
<Chaos>0.801069</Chaos>
<Notes>352.000000</Notes>
<TapsAndHolds>335</TapsAndHolds>
<Jumps>19</Jumps>
<Holds>35</Holds>
<Mines>0</Mines>
<Hands>0</Hands>
<Rolls>0</Rolls>
<Lifts>0</Lifts>
<Fakes>0</Fakes>
</RadarValues>
<LifeRemainingSeconds>0.000000</LifeRemainingSeconds>
<Disqualified>0</Disqualified>
<Pad>33</Pad>
<StageGuid>571d8068-8695-4220-a6d5-3c36f64abbf6</StageGuid>
<Guid>58e622c6-561d-46ec-ae4f-41135f48b137</Guid>
</HighScore>
</HighScoreForASongAndSteps>
</RecentSongScores>
</Stats>
