<?xml version="1.0" encoding="UTF-8" ?>

<Stats>
<MachineGuid>403d15c592378cca</MachineGuid>
<RecentSongScores>
<HighScoreForASongAndSteps>
<Song Dir='Songs/Mungyodance/Hide and Seek (Renard&apos;s Remix)/'/>
<Steps Difficulty='Medium' StepsType='dance-single'/>
<HighScore>
<Name></Name>
<Grade>Tier11</Grade>
<Score>57</Score>
<PercentDP>0.780400</PercentDP>
<SurviveSeconds>112.563889</SurviveSeconds>
<MaxCombo>163</MaxCombo>
<StageAward></StageAward>
<PeakComboAward></PeakComboAward>
<Modifiers>NoHideLights, C420, FailImmediateContinue, Overhead, Default</Modifiers>
<DateTime>2025-08-20 18:02:08</DateTime>
<PlayerGuid>d876307e83faa0ea</PlayerGuid>
<MachineGuid>403d15c592378cca</MachineGuid>
<ProductID>1</ProductID>
<TapNoteScores>
<HitMine>0</HitMine>
<AvoidMine>0</AvoidMine>
<CheckpointMiss>0</CheckpointMiss>
<Miss>8</Miss>
<W5>0</W5>
<W4>1</W4>
<W3>38</W3>
<W2>80</W2>
<W1>186</W1>
<CheckpointHit>0</CheckpointHit>
</TapNoteScores>
<HoldNoteScores>
<LetGo>5</LetGo>
<Held>10</Held>
<MissedHold>0</MissedHold>
</HoldNoteScores>
<RadarValues>
<Stream>0.833811</Stream>
<Voltage>0.433811</Voltage>
<Air>0.666667</Air>
<Freeze>0.666667</Freeze>
<Chaos>0.780488</Chaos>
<Notes>339.000000</Notes>
<TapsAndHolds>305</TapsAndHolds>
<Jumps>30</Jumps>
<Holds>10</Holds>
<Mines>0</Mines>
<Hands>0</Hands>
<Rolls>0</Rolls>
<Lifts>0</Lifts>
<Fakes>0</Fakes>
</RadarValues>
<LifeRemainingSeconds>0.000000</LifeRemainingSeconds>
<Disqualified>0</Disqualified>
<Pad>33</Pad>
<StageGuid>8fcb9356-dce6-45bd-a254-85c3a720259e</StageGuid>
<Guid>6310c600-a5f4-41ae-a742-ced19f2435be</Guid>
</HighScore>
</HighScoreForASongAndSteps>
</RecentSongScores>
</Stats>
