<?xml version="1.0" encoding="UTF-8" ?>

<Stats>
<MachineGuid>403d15c592378cca</MachineGuid>
<RecentSongScores>
<HighScoreForASongAndSteps>
<Song Dir='Songs/Tech-Bit Adventures/Opening Title (James Landino Remix)/'/>
<Steps Difficulty='Challenge' StepsType='dance-single'/>
<HighScore>
<Name></Name>
<Grade>Tier13</Grade>
<Score>72</Score>
<PercentDP>0.719800</PercentDP>
<SurviveSeconds>149.327576</SurviveSeconds>
<MaxCombo>69</MaxCombo>
<StageAward></StageAward>
<PeakComboAward></PeakComboAward>
<Modifiers>NoHideLights, C565, 10% Mini, FailImmediateContinue, Overhead, Default</Modifiers>
<DateTime>2025-04-29 18:32:59</DateTime>
<PlayerGuid>4ad3a19834ee56bd</PlayerGuid>
<MachineGuid>403d15c592378cca</MachineGuid>
<ProductID>1</ProductID>
<TapNoteScores>
<HitMine>2</HitMine>
<AvoidMine>0</AvoidMine>
<CheckpointMiss>0</CheckpointMiss>
<Miss>14</Miss>
<W5>5</W5>
<W4>11</W4>
<W3>134</W3>
<W2>133</W2>
<W1>223</W1>
<CheckpointHit>0</CheckpointHit>
</TapNoteScores>
<HoldNoteScores>
<LetGo>1</LetGo>
<Held>137</Held>
<MissedHold>6</MissedHold>
</HoldNoteScores>
<RadarValues>
<Stream>0.685606</Stream>
<Voltage>0.170299</Voltage>
<Air>0.250000</Air>
<Freeze>0.948529</Freeze>
<Chaos>0.719880</Chaos>
<Notes>508.000000</Notes>
<TapsAndHolds>501</TapsAndHolds>
<Jumps>7</Jumps>
<Holds>129</Holds>
<Mines>23</Mines>
<Hands>5</Hands>
<Rolls>8</Rolls>
<Lifts>0</Lifts>
<Fakes>0</Fakes>
</RadarValues>
<LifeRemainingSeconds>0.000000</LifeRemainingSeconds>
<Disqualified>0</Disqualified>
<Pad>33</Pad>
<StageGuid>e4d638bd-6956-49d7-a50f-34257490f6a1</StageGuid>
<Guid>1a723395-87a3-4a14-a75c-5d0100c5ca7c</Guid>
</HighScore>
</HighScoreForASongAndSteps>
</RecentSongScores>
</Stats>
