<?xml version="1.0" encoding="UTF-8" ?>

<Stats>
<MachineGuid>403d15c592378cca</MachineGuid>
<RecentSongScores>
<HighScoreForASongAndSteps>
<Song Dir='Songs/Misc. Collected/One By One/'/>
<Steps Difficulty='Medium' StepsType='dance-single'/>
<HighScore>
<Name></Name>
<Grade>Tier11</Grade>
<Score>74</Score>
<PercentDP>0.793600</PercentDP>
<SurviveSeconds>133.127075</SurviveSeconds>
<MaxCombo>175</MaxCombo>
<StageAward></StageAward>
<PeakComboAward></PeakComboAward>
<Modifiers>NoHideLights, C420, FailImmediateContinue, Overhead, Default</Modifiers>
<DateTime>2025-08-19 16:38:06</DateTime>
<PlayerGuid>d876307e83faa0ea</PlayerGuid>
<MachineGuid>403d15c592378cca</MachineGuid>
<ProductID>1</ProductID>
<TapNoteScores>
<HitMine>0</HitMine>
<AvoidMine>0</AvoidMine>
<CheckpointMiss>0</CheckpointMiss>
<Miss>5</Miss>
<W5>1</W5>
<W4>1</W4>
<W3>63</W3>
<W2>194</W2>
<W1>170</W1>
<CheckpointHit>0</CheckpointHit>
</TapNoteScores>
<HoldNoteScores>
<LetGo>0</LetGo>
<Held>35</Held>
<MissedHold>0</MissedHold>
</HoldNoteScores>
<RadarValues>
<Stream>0.838710</Stream>
<Voltage>0.401773</Voltage>
<Air>0.000000</Air>
<Freeze>1.000000</Freeze>
<Chaos>0.793603</Chaos>
<Notes>428.000000</Notes>
<TapsAndHolds>428</TapsAndHolds>
<Jumps>0</Jumps>
<Holds>35</Holds>
<Mines>0</Mines>
<Hands>0</Hands>
<Rolls>0</Rolls>
<Lifts>0</Lifts>
<Fakes>2</Fakes>
</RadarValues>
<LifeRemainingSeconds>0.000000</LifeRemainingSeconds>
<Disqualified>0</Disqualified>
<Pad>33</Pad>
<StageGuid>1cc673e5-0219-4748-a24b-70bbc77cc461</StageGuid>
<Guid>592263d3-379f-46d8-a47e-63736d93677d</Guid>
</HighScore>
</HighScoreForASongAndSteps>
</RecentSongScores>
</Stats>
