<?xml version="1.0" encoding="UTF-8" ?>

<Stats>
<MachineGuid>403d15c592378cca</MachineGuid>
<RecentSongScores>
<HighScoreForASongAndSteps>
<Song Dir='Songs/Misc. Collected (DDR Ratings)/WE NO SPEAK AMERICANO/'/>
<Steps Difficulty='Hard' StepsType='dance-single'/>
<HighScore>
<Name></Name>
<Grade>Tier14</Grade>
<Score>40</Score>
<PercentDP>0.667600</PercentDP>
<SurviveSeconds>102.529930</SurviveSeconds>
<MaxCombo>68</MaxCombo>
<StageAward></StageAward>
<PeakComboAward></PeakComboAward>
<Modifiers>NoHideLights, C570, 10% Mini, FailImmediateContinue, Overhead, Default</Modifiers>
<DateTime>2025-04-17 16:55:49</DateTime>
<PlayerGuid>4ad3a19834ee56bd</PlayerGuid>
<MachineGuid>403d15c592378cca</MachineGuid>
<ProductID>1</ProductID>
<TapNoteScores>
<HitMine>0</HitMine>
<AvoidMine>0</AvoidMine>
<CheckpointMiss>0</CheckpointMiss>
<Miss>10</Miss>
<W5>1</W5>
<W4>4</W4>
<W3>53</W3>
<W2>77</W2>
<W1>110</W1>
<CheckpointHit>0</CheckpointHit>
</TapNoteScores>
<HoldNoteScores>
<LetGo>0</LetGo>
<Held>10</Held>
<MissedHold>1</MissedHold>
</HoldNoteScores>
<RadarValues>
<Stream>0.750000</Stream>
<Voltage>0.249472</Voltage>
<Air>0.882353</Air>
<Freeze>0.909091</Freeze>
<Chaos>0.667669</Chaos>
<Notes>261.000000</Notes>
<TapsAndHolds>244</TapsAndHolds>
<Jumps>17</Jumps>
<Holds>10</Holds>
<Mines>0</Mines>
<Hands>0</Hands>
<Rolls>0</Rolls>
<Lifts>0</Lifts>
<Fakes>0</Fakes>
</RadarValues>
<LifeRemainingSeconds>0.000000</LifeRemainingSeconds>
<Disqualified>0</Disqualified>
<Pad>33</Pad>
<StageGuid>17950459-f419-4f1c-adb0-e2159516d5eb</StageGuid>
<Guid>4b45a433-8c26-47a6-a650-73fbb223dff8</Guid>
</HighScore>
</HighScoreForASongAndSteps>
</RecentSongScores>
</Stats>
