<?xml version="1.0" encoding="UTF-8" ?>

<Stats>
<MachineGuid>403d15c592378cca</MachineGuid>
<RecentSongScores>
<HighScoreForASongAndSteps>
<Song Dir='Songs/Anthem Series - The Boys/Cake by the Ocean/'/>
<Steps Difficulty='Challenge' StepsType='dance-single'/>
<HighScore>
<Name></Name>
<Grade>Tier10</Grade>
<Score>84</Score>
<PercentDP>0.813300</PercentDP>
<SurviveSeconds>139.059433</SurviveSeconds>
<MaxCombo>107</MaxCombo>
<StageAward></StageAward>
<PeakComboAward></PeakComboAward>
<Modifiers>NoHideLights, C575, 10% Mini, FailImmediateContinue, Overhead, Default</Modifiers>
<DateTime>2025-07-06 12:03:25</DateTime>
<PlayerGuid>4ad3a19834ee56bd</PlayerGuid>
<MachineGuid>403d15c592378cca</MachineGuid>
<ProductID>1</ProductID>
<TapNoteScores>
<HitMine>1</HitMine>
<AvoidMine>0</AvoidMine>
<CheckpointMiss>0</CheckpointMiss>
<Miss>12</Miss>
<W5>5</W5>
<W4>6</W4>
<W3>73</W3>
<W2>125</W2>
<W1>284</W1>
<CheckpointHit>0</CheckpointHit>
</TapNoteScores>
<HoldNoteScores>
<LetGo>1</LetGo>
<Held>197</Held>
<MissedHold>3</MissedHold>
</HoldNoteScores>
<RadarValues>
<Stream>0.813589</Stream>
<Voltage>0.197792</Voltage>
<Air>0.666667</Air>
<Freeze>0.984211</Freeze>
<Chaos>0.813314</Chaos>
<Notes>553.000000</Notes>
<TapsAndHolds>493</TapsAndHolds>
<Jumps>64</Jumps>
<Holds>187</Holds>
<Mines>11</Mines>
<Hands>0</Hands>
<Rolls>10</Rolls>
<Lifts>0</Lifts>
<Fakes>0</Fakes>
</RadarValues>
<LifeRemainingSeconds>0.000000</LifeRemainingSeconds>
<Disqualified>0</Disqualified>
<Pad>33</Pad>
<StageGuid>3cd9347b-0ef1-44d4-af5c-7ee80549edcc</StageGuid>
<Guid>3041e057-ea13-4429-a785-3cf94c9a7600</Guid>
</HighScore>
</HighScoreForASongAndSteps>
</RecentSongScores>
</Stats>
