<?xml version="1.0" encoding="UTF-8" ?>

<Stats>
<MachineGuid>403d15c592378cca</MachineGuid>
<RecentSongScores>
<HighScoreForASongAndSteps>
<Song Dir='Songs/Misc. Collected/Driver/'/>
<Steps Difficulty='Challenge' StepsType='dance-single'/>
<HighScore>
<Name></Name>
<Grade>Tier11</Grade>
<Score>70</Score>
<PercentDP>0.778900</PercentDP>
<SurviveSeconds>102.597450</SurviveSeconds>
<MaxCombo>119</MaxCombo>
<StageAward></StageAward>
<PeakComboAward></PeakComboAward>
<Modifiers>NoHideLights, C585, 10% Mini, FailImmediateContinue, Overhead, Default</Modifiers>
<DateTime>2025-12-14 13:04:19</DateTime>
<PlayerGuid>4ad3a19834ee56bd</PlayerGuid>
<MachineGuid>403d15c592378cca</MachineGuid>
<ProductID>1</ProductID>
<TapNoteScores>
<HitMine>0</HitMine>
<AvoidMine>0</AvoidMine>
<CheckpointMiss>0</CheckpointMiss>
<Miss>8</Miss>
<W5>1</W5>
<W4>7</W4>
<W3>73</W3>
<W2>102</W2>
<W1>233</W1>
<CheckpointHit>0</CheckpointHit>
</TapNoteScores>
<HoldNoteScores>
<LetGo>0</LetGo>
<Held>31</Held>
<MissedHold>0</MissedHold>
</HoldNoteScores>
<RadarValues>
<Stream>0.792608</Stream>
<Voltage>0.224787</Voltage>
<Air>0.746032</Air>
<Freeze>1.000000</Freeze>
<Chaos>0.778901</Chaos>
<Notes>475.000000</Notes>
<TapsAndHolds>416</TapsAndHolds>
<Jumps>61</Jumps>
<Holds>31</Holds>
<Mines>0</Mines>
<Hands>0</Hands>
<Rolls>0</Rolls>
<Lifts>0</Lifts>
<Fakes>0</Fakes>
</RadarValues>
<LifeRemainingSeconds>0.000000</LifeRemainingSeconds>
<Disqualified>0</Disqualified>
<Pad>33</Pad>
<StageGuid>4ca8b983-97e2-4fbb-abb8-7173f9e16e7f</StageGuid>
<Guid>b4e93d6f-3aa9-4cfb-ac71-4ca585089367</Guid>
</HighScore>
</HighScoreForASongAndSteps>
</RecentSongScores>
</Stats>
