{"GameMode":"FA+","MachineGuid":"2795733f34c89ebd","ProductID":"ITGmania","ProductVersion":"0.7.0","Score":{"DateTime":"2025-01-20 13:43:55","Disqualified":false,"Grade":"Tier04","Guid":"8c122947-33a5-4314-a4f6-e6a88b09fef6","HoldNoteScores":{"Held":0,"LetGo":0,"MissedHold":0},"MaxCombo":199,"Modifiers":"C585, 10% Mini, NoMines, FailImmediateContinue, Overhead, Default, No W5","PercentDP":0.96990007162094116,"PlayerGuid":"7d658d42d132c3a6","Radar":{"Hands":0,"Holds":0,"Jumps":7,"Mines":0,"Notes":319,"Rolls":0,"TapsAndHolds":312},"Score":92776748,"SurviveSeconds":95.783645629882812,"TapNoteScores":{"AvoidMine":0,"CheckpointHit":0,"CheckpointMiss":0,"HitMine":0,"Miss":1,"W1":242,"W2":42,"W3":27,"W4":1,"W5":0}},"Song":{"Artist":"BUS\u2605STOP","BPM":[144,144],"Dir":"/Songs/DDR 1stMix-5thMix/KICK THE CAN/","Group":"DDR 1stMix-5thMix","MusicLengthSeconds":94.971000671386719,"RandomBPM":false,"Title":"KICK THE CAN","TranslitArtist":"BUS\u2605STOP","TranslitTitle":"KICK THE CAN"},"Steps":{"AuthorCredit":"","Description":"","Difficulty":"Hard","Meter":7,"Radar":{"Hands":0,"Holds":0,"Jumps":7,"Mines":0,"Notes":320,"Rolls":0,"TapsAndHolds":313},"StepsType":"dance-single"},"Theme":"Simply Love","ThemeVersion":"5.3.0 for ITGmania","Version":1}
