{"GameMode":"FA+","MachineGuid":"2795733f34c89ebd","ProductID":"ITGmania","ProductVersion":"0.7.0","Score":{"DateTime":"2025-03-30 12:55:26","Disqualified":false,"Grade":"Tier04","Guid":"8002c208-e6aa-4939-a76a-5f56a4a4914e","HoldNoteScores":{"Held":6,"LetGo":0,"MissedHold":0},"MaxCombo":330,"Modifiers":"C585, 10% Mini, NoMines, FailImmediateContinue, Overhead, Default, No W5","PercentDP":0.97160005569458008,"PlayerGuid":"7d658d42d132c3a6","Radar":{"Hands":0,"Holds":6,"Jumps":11,"Mines":0,"Notes":653,"Rolls":0,"TapsAndHolds":641},"Score":92014885,"SurviveSeconds":135.46516418457031,"TapNoteScores":{"AvoidMine":0,"CheckpointHit":0,"CheckpointMiss":0,"HitMine":0,"Miss":1,"W1":488,"W2":102,"W3":39,"W4":12,"W5":0}},"Song":{"Artist":"Aqua","BPM":[139.97000122070312,139.97000122070312],"Dir":"/Songs/Misc Charts/Doctor Jones/","Group":"Misc Charts","MusicLengthSeconds":133.38400268554688,"RandomBPM":false,"Title":"Doctor Jones","TranslitArtist":"Aqua","TranslitTitle":"Doctor Jones"},"Steps":{"AuthorCredit":"J. Frederick","Description":"J. Frederick","Difficulty":"Challenge","Meter":9,"Radar":{"Hands":0,"Holds":6,"Jumps":12,"Mines":0,"Notes":654,"Rolls":0,"TapsAndHolds":642},"StepsType":"dance-single"},"Theme":"Simply Love","ThemeVersion":"5.3.0 for ITGmania","Version":1}
